lenstools/__init__.py
lenstools/catalog/__init__.py
lenstools/catalog/catalog.py
lenstools/catalog/generateCatalog.py
lenstools/catalog/shear.py
lenstools/data/CFHTemu1.txt
lenstools/data/CFHTemu1_array.npy
lenstools/data/catalog_default.ini
lenstools/data/cluster_default.ini
lenstools/data/contour.cfg
lenstools/data/dummy_glass_big_endian.dat
lenstools/data/dummy_glass_little_endian.dat
lenstools/data/environment_default.ini
lenstools/data/job_default.ini
lenstools/data/lens_default.ini
lenstools/data/lightcone_default.ini
lenstools/data/los_default.ini
lenstools/data/power_spectrum_default.ini
lenstools/data/reconstruction_default.ini
lenstools/data/telescopic_default.ini
lenstools/extern/__init__.py
lenstools/extern/_design.cpython-37m-darwin.so
lenstools/extern/_gadget2.cpython-37m-darwin.so
lenstools/extern/_nbody.cpython-37m-darwin.so
lenstools/extern/_nicaea.cpython-37m-darwin.so
lenstools/extern/_pixelize.cpython-37m-darwin.so
lenstools/extern/_topology.cpython-37m-darwin.so
lenstools/extern/azimuth.h
lenstools/extern/coordinates.h
lenstools/extern/design.h
lenstools/extern/differentials.h
lenstools/extern/gadget2.h
lenstools/extern/grid.h
lenstools/extern/lenstoolsPy3.h
lenstools/extern/minkowski.h
lenstools/extern/nicaea_wrappers.h
lenstools/extern/peaks.h
lenstools/image/__init__.py
lenstools/image/cmblens.py
lenstools/image/convergence.py
lenstools/image/flexion.py
lenstools/image/io.py
lenstools/image/noise.py
lenstools/image/shear.py
lenstools/legacy/__init__.py
lenstools/legacy/constraints.py
lenstools/legacy/design.py
lenstools/legacy/ensemble.py
lenstools/legacy/index.py
lenstools/observations/__init__.py
lenstools/observations/cfhtlens.py
lenstools/pipeline/__init__.py
lenstools/pipeline/cluster.py
lenstools/pipeline/deploy.py
lenstools/pipeline/remote.py
lenstools/pipeline/settings.py
lenstools/pipeline/simulation.py
lenstools/scripts/__init__.py
lenstools/scripts/cmblens.py
lenstools/scripts/confidencecontour.py
lenstools/scripts/cutplanes.py
lenstools-1.2.dist-info/METADATA
lenstools-1.2.dist-info/WHEEL
lenstools-1.2.dist-info/top_level.txt
lenstools-1.2.dist-info/RECORD
