Metadata-Version: 2.1
Name: lenstools
Version: 1.2
Summary: Toolkit for Weak Gravitational Lensing analysis
Home-page: http://lenstools.readthedocs.org
Author: Andrea Petri
Author-email: apetri@phys.columbia.edu
License: MIT
Download-URL: https://github.com/apetri/LensTools/archive/1.2.tar.gz
Platform: UNKNOWN
Classifier: Development Status :: 4 - Beta
Classifier: Intended Audience :: Science/Research
Classifier: Operating System :: OS Independent
Classifier: Programming Language :: Python
Classifier: Programming Language :: C
Classifier: License :: OSI Approved :: MIT License
Requires-Dist: numpy
Requires-Dist: scipy
Requires-Dist: pandas
Requires-Dist: matplotlib
Requires-Dist: astropy
Requires-Dist: emcee (<=2.2.1)
